{
	"version": 3,
	"title": "CJSM palette",
	"settings": {
		"color": {
			"palette": [
				{
					"slug": "colour-1",
					"color": "var(--colour-primary)",
					"name": "Colour 1"
				},
				{
					"slug": "colour-2",
					"color": "var(--colour-primary-accent)",
					"name": "Colour 2"
				},
				{
					"slug": "colour-3",
					"color": "var(--colour-secondary)",
					"name": "Colour 3"
				},
				{
					"slug": "colour-4",
					"color": "var(--colour-secondary-accent)",
					"name": "Colour 4"
				},
				{
					"slug": "greyscale-a",
					"color": "var(--colour-background)",
					"name": "Greyscale A"
				},
				{
					"slug": "greyscale-h",
					"color": "var(--colour-background-secondary)",
					"name": "Greyscale H"
				},
				{
					"slug": "greyscale-q",
					"color": "var(--colour-foreground-secondary)",
					"name": "Greyscale Q"
				},
				{
					"slug": "greyscale-z",
					"color": "var(--colour-foreground)",
					"name": "Greyscale Z"
				}
			]
		}
	}
}
